pygzipf.cpython-310-x86_64-linux-gnu.so
libgzipf_python-20240422.dist-info/RECORD
libgzipf_python-20240422.dist-info/WHEEL
libgzipf_python-20240422.dist-info/METADATA
libgzipf_python-20240422.dist-info/top_level.txt
